<?xml version="1.0" encoding="ISO-8859-1"?> 
	<TRIAL ID="309" AGE="25" GENDER="m" DURATION="19">
		<CONTEXT ID ="1" SEQ="1681" STATUS="ok" AGREEMENT="no" ANNOTATOR="1"  SIZE1="7"  SIZE2="0" WORD-STRING ="o restaurante na esquina da rua anchieta">
			<ATTRIBUTE-SET1 TARGET.ID="rest3">
				<ATTRIBUTE NAME="type" VALUE="restaurant" />
				<ATTRIBUTE NAME="in" VALUE="str6" />
				<ATTRIBUTE NAME="d1.id" VALUE="str6" />
				<ATTRIBUTE NAME="d1.type" VALUE="street" />
				<ATTRIBUTE NAME="d1.name" VALUE="rua anchieta" />
				<ATTRIBUTE NAME="d1.other" VALUE="corner" />
			</ATTRIBUTE-SET1>
		</CONTEXT>
		<CONTEXT ID ="2" SEQ="1684" STATUS="ok" AGREEMENT="yes" ANNOTATOR="1"  SIZE1="6"  SIZE2="0" WORD-STRING ="o cafe no calcadao da rua nova da trindade">
			<ATTRIBUTE-SET1 TARGET.ID="cafe1">
				<ATTRIBUTE NAME="type" VALUE="cafe" />
				<ATTRIBUTE NAME="in" VALUE="str1" />
				<ATTRIBUTE NAME="d1.id" VALUE="str1" />
				<ATTRIBUTE NAME="d1.type" VALUE="street" />
				<ATTRIBUTE NAME="d1.name" VALUE="rua nova da trindade" />
			</ATTRIBUTE-SET1>
		</CONTEXT>
		<CONTEXT ID ="3" SEQ="1683" STATUS="ok" AGREEMENT="no" ANNOTATOR="1"  SIZE1="10"  SIZE2="0" WORD-STRING ="a farmacia an esquina da rua do ouro com a rua da vitoria">
			<ATTRIBUTE-SET1 TARGET.ID="drug3">
				<ATTRIBUTE NAME="type" VALUE="drugstore" />
				<ATTRIBUTE NAME="between" VALUE="[str11,str12]" />
				<ATTRIBUTE NAME="d1.id" VALUE="str11" />
				<ATTRIBUTE NAME="d1.type" VALUE="street" />
				<ATTRIBUTE NAME="d1.name" VALUE="rua do ouro" />
				<ATTRIBUTE NAME="d1.other" VALUE="corner" />
				<ATTRIBUTE NAME="d2.id" VALUE="str12" />
				<ATTRIBUTE NAME="d2.type" VALUE="street" />
				<ATTRIBUTE NAME="d2.name" VALUE="rua da vitoria" />
			</ATTRIBUTE-SET1>
		</CONTEXT>
		<CONTEXT ID ="4" SEQ="1682" STATUS="edited" AGREEMENT="no" ANNOTATOR="1"  SIZE1="7"  SIZE2="0" WORD-STRING ="a igreja que fica na travessa da rua do crucifixo">
			<ATTRIBUTE-SET1 TARGET.ID="chur3">
				<ATTRIBUTE NAME="type" VALUE="church" />
				<ATTRIBUTE NAME="in" VALUE="str14" />
				<ATTRIBUTE NAME="d1.id" VALUE="str14" />
				<ATTRIBUTE NAME="d1.type" VALUE="street" />
				<ATTRIBUTE NAME="d1.name" VALUE="rua do crucifixo" />
				<ATTRIBUTE NAME="d1.other" VALUE="corner" />
			</ATTRIBUTE-SET1>
		</CONTEXT>
		<CONTEXT ID ="5" SEQ="1685" STATUS="ok" AGREEMENT="no" ANNOTATOR="1"  SIZE1="6"  SIZE2="0" WORD-STRING ="o pub em frente ao restaurante aqui ha peixe">
			<ATTRIBUTE-SET1 TARGET.ID="pub1">
				<ATTRIBUTE NAME="type" VALUE="pub" />
				<ATTRIBUTE NAME="in-front-of" VALUE="rest1" />
				<ATTRIBUTE NAME="d1.id" VALUE="rest1" />
				<ATTRIBUTE NAME="d1.type" VALUE="restaurant" />
				<ATTRIBUTE NAME="d1.name" VALUE="aqui ha peixe" />
			</ATTRIBUTE-SET1>
		</CONTEXT>
		<CONTEXT ID ="6" SEQ="1686" STATUS="ok" AGREEMENT="no" ANNOTATOR="2"  SIZE1="6"  SIZE2="0" WORD-STRING ="a igreja em frente ao parque chiado">
			<ATTRIBUTE-SET1 TARGET.ID="chur2">
				<ATTRIBUTE NAME="type" VALUE="church" />
				<ATTRIBUTE NAME="in-front-of" VALUE="park1" />
				<ATTRIBUTE NAME="d1.id" VALUE="park1" />
				<ATTRIBUTE NAME="d1.type" VALUE="park" />
				<ATTRIBUTE NAME="d1.name" VALUE="chiado" />
			</ATTRIBUTE-SET1>
		</CONTEXT>
		<CONTEXT ID ="7" SEQ="1689" STATUS="ok" AGREEMENT="yes" ANNOTATOR="1"  SIZE1="3"  SIZE2="6" WORD-STRING ="os restaurantes aqui ha peixe, ou o da rua garrett">
			<ATTRIBUTE-SET1 TARGET.ID="rest1">
				<ATTRIBUTE NAME="type" VALUE="restaurant" />
				<ATTRIBUTE NAME="name" VALUE="aqui ha peixe" />
			</ATTRIBUTE-SET1>
			<ATTRIBUTE-SET2 TARGET.ID="rest2">
				<ATTRIBUTE NAME="type" VALUE="restaurant" />
				<ATTRIBUTE NAME="in" VALUE="str3" />
				<ATTRIBUTE NAME="d1.id" VALUE="str3" />
				<ATTRIBUTE NAME="d1.type" VALUE="street" />
				<ATTRIBUTE NAME="d1.name" VALUE="rua garret" />
			</ATTRIBUTE-SET2>
		</CONTEXT>
		<CONTEXT ID ="8" SEQ="1688" STATUS="ok" AGREEMENT="yes" ANNOTATOR="1"  SIZE1="7"  SIZE2="0" WORD-STRING ="a farmacia internacional da rua do ouro">
			<ATTRIBUTE-SET1 TARGET.ID="drug2">
				<ATTRIBUTE NAME="type" VALUE="drugstore" />
				<ATTRIBUTE NAME="name" VALUE="internacional" />
				<ATTRIBUTE NAME="in" VALUE="str11" />
				<ATTRIBUTE NAME="d1.id" VALUE="str11" />
				<ATTRIBUTE NAME="d1.type" VALUE="street" />
				<ATTRIBUTE NAME="d1.name" VALUE="rua do ouro" />
			</ATTRIBUTE-SET1>
		</CONTEXT>
		<CONTEXT ID ="9" SEQ="1687" STATUS="ok" AGREEMENT="yes" ANNOTATOR="1"  SIZE1="6"  SIZE2="6" WORD-STRING ="as farmacias da rua do ouro">
			<ATTRIBUTE-SET1 TARGET.ID="drug3">
				<ATTRIBUTE NAME="type" VALUE="drugstore" />
				<ATTRIBUTE NAME="in" VALUE="str11" />
				<ATTRIBUTE NAME="d1.id" VALUE="str11" />
				<ATTRIBUTE NAME="d1.type" VALUE="street" />
				<ATTRIBUTE NAME="d1.name" VALUE="rua do ouro" />
			</ATTRIBUTE-SET1>
			<ATTRIBUTE-SET2 TARGET.ID="drug4">
				<ATTRIBUTE NAME="type" VALUE="drugstore" />
				<ATTRIBUTE NAME="in" VALUE="str11" />
				<ATTRIBUTE NAME="d1.id" VALUE="str11" />
				<ATTRIBUTE NAME="d1.type" VALUE="street" />
				<ATTRIBUTE NAME="d1.name" VALUE="rua do ouro" />
			</ATTRIBUTE-SET2>
		</CONTEXT>
		<CONTEXT ID ="10" SEQ="1690" STATUS="ok" AGREEMENT="yes" ANNOTATOR="1"  SIZE1="3"  SIZE2="3" WORD-STRING ="os restaurantes o sacramento ou a taberna do chiado">
			<ATTRIBUTE-SET1 TARGET.ID="rest4">
				<ATTRIBUTE NAME="type" VALUE="restaurant" />
				<ATTRIBUTE NAME="name" VALUE="o sacramento" />
			</ATTRIBUTE-SET1>
			<ATTRIBUTE-SET2 TARGET.ID="rest5">
				<ATTRIBUTE NAME="type" VALUE="restaurant" />
				<ATTRIBUTE NAME="name" VALUE="taberna do chiado" />
			</ATTRIBUTE-SET2>
		</CONTEXT>
		<CONTEXT ID ="11" SEQ="1691" STATUS="ok" AGREEMENT="yes" ANNOTATOR="1"  SIZE1="7"  SIZE2="0" WORD-STRING ="o restaurante kaffeehaus na rua anchieta">
			<ATTRIBUTE-SET1 TARGET.ID="rest3">
				<ATTRIBUTE NAME="type" VALUE="restaurant" />
				<ATTRIBUTE NAME="name" VALUE="kaffeehaus" />
				<ATTRIBUTE NAME="in" VALUE="str6" />
				<ATTRIBUTE NAME="d1.id" VALUE="str6" />
				<ATTRIBUTE NAME="d1.type" VALUE="street" />
				<ATTRIBUTE NAME="d1.name" VALUE="rua anchieta" />
			</ATTRIBUTE-SET1>
		</CONTEXT>
		<CONTEXT ID ="12" SEQ="1694" STATUS="ok" AGREEMENT="yes" ANNOTATOR="1"  SIZE1="7"  SIZE2="0" WORD-STRING ="o cafe no final da rua garrett">
			<ATTRIBUTE-SET1 TARGET.ID="cafe1">
				<ATTRIBUTE NAME="type" VALUE="cafe" />
				<ATTRIBUTE NAME="in" VALUE="str3" />
				<ATTRIBUTE NAME="d1.id" VALUE="str3" />
				<ATTRIBUTE NAME="d1.type" VALUE="street" />
				<ATTRIBUTE NAME="d1.name" VALUE="rua garret" />
				<ATTRIBUTE NAME="d1.other" VALUE="end" />
			</ATTRIBUTE-SET1>
		</CONTEXT>
		<CONTEXT ID ="13" SEQ="1693" STATUS="edited" AGREEMENT="no" ANNOTATOR="1"  SIZE1="6"  SIZE2="2" WORD-STRING ="os restaurantes o sacramento, na calcado do sacramento, ou a taberna do chiado">
			<ATTRIBUTE-SET1 TARGET.ID="rest4">
				<ATTRIBUTE NAME="type" VALUE="restaurant" />
				<ATTRIBUTE NAME="name" VALUE="o sacramento" />
				<ATTRIBUTE NAME="in" VALUE="str16" />
				<ATTRIBUTE NAME="d1.id" VALUE="str16" />
				<ATTRIBUTE NAME="d1.name" VALUE="calcada do sacramento" />
			</ATTRIBUTE-SET1>
			<ATTRIBUTE-SET2 TARGET.ID="rest5">
				<ATTRIBUTE NAME="name" VALUE="taberna do chiado" />
			</ATTRIBUTE-SET2>
		</CONTEXT>
		<CONTEXT ID ="14" SEQ="1692" STATUS="edited" AGREEMENT="no" ANNOTATOR="1"  SIZE1="7"  SIZE2="0" WORD-STRING ="a igreja na travessa da rua do ouro">
			<ATTRIBUTE-SET1 TARGET.ID="chur3">
				<ATTRIBUTE NAME="type" VALUE="church" />
				<ATTRIBUTE NAME="in" VALUE="str11" />
				<ATTRIBUTE NAME="d1.id" VALUE="str11" />
				<ATTRIBUTE NAME="d1.type" VALUE="street" />
				<ATTRIBUTE NAME="d1.name" VALUE="rua do ouro" />
				<ATTRIBUTE NAME="d1.other" VALUE="corner" />
			</ATTRIBUTE-SET1>
		</CONTEXT>
		<CONTEXT ID ="15" SEQ="1695" STATUS="ok" AGREEMENT="yes" ANNOTATOR="1"  SIZE1="7"  SIZE2="0" WORD-STRING ="o pub ao final da rua da trindade">
			<ATTRIBUTE-SET1 TARGET.ID="pub1">
				<ATTRIBUTE NAME="type" VALUE="pub" />
				<ATTRIBUTE NAME="in" VALUE="str17" />
				<ATTRIBUTE NAME="d1.id" VALUE="str17" />
				<ATTRIBUTE NAME="d1.type" VALUE="street" />
				<ATTRIBUTE NAME="d1.name" VALUE="rua da trindade" />
				<ATTRIBUTE NAME="d1.other" VALUE="end" />
			</ATTRIBUTE-SET1>
		</CONTEXT>
		<CONTEXT ID ="16" SEQ="1696" STATUS="edited" AGREEMENT="no" ANNOTATOR="1"  SIZE1="5"  SIZE2="7" WORD-STRING ="as igrejas do calcada do sacramento ou da travessa da rua do ouro">
			<ATTRIBUTE-SET1 TARGET.ID="chur2">
				<ATTRIBUTE NAME="type" VALUE="church" />
				<ATTRIBUTE NAME="in" VALUE="str16" />
				<ATTRIBUTE NAME="d1.id" VALUE="str16" />
				<ATTRIBUTE NAME="d1.name" VALUE="calcada do sacramento" />
			</ATTRIBUTE-SET1>
			<ATTRIBUTE-SET2 TARGET.ID="chur3">
				<ATTRIBUTE NAME="type" VALUE="church" />
				<ATTRIBUTE NAME="in" VALUE="str11" />
				<ATTRIBUTE NAME="d1.id" VALUE="str11" />
				<ATTRIBUTE NAME="d1.type" VALUE="street" />
				<ATTRIBUTE NAME="d1.name" VALUE="rua do ouro" />
				<ATTRIBUTE NAME="d1.other" VALUE="corner" />
			</ATTRIBUTE-SET2>
		</CONTEXT>
		<CONTEXT ID ="17" SEQ="1699" STATUS="edited" AGREEMENT="no" ANNOTATOR="1"  SIZE1="8"  SIZE2="7" WORD-STRING ="os restaurantes aqui ha peixe na esquina da rua trindade, ou a vitaminas garret na rua garrett">
			<ATTRIBUTE-SET1 TARGET.ID="rest1">
				<ATTRIBUTE NAME="type" VALUE="restaurant" />
				<ATTRIBUTE NAME="name" VALUE="aqui ha peixe" />
				<ATTRIBUTE NAME="in" VALUE="str17" />
				<ATTRIBUTE NAME="d1.id" VALUE="str17" />
				<ATTRIBUTE NAME="d1.type" VALUE="street" />
				<ATTRIBUTE NAME="d1.name" VALUE="rua da trindade" />
				<ATTRIBUTE NAME="d1.other" VALUE="corner" />
			</ATTRIBUTE-SET1>
			<ATTRIBUTE-SET2 TARGET.ID="rest2">
				<ATTRIBUTE NAME="type" VALUE="restaurant" />
				<ATTRIBUTE NAME="name" VALUE="vitaminas garret" />
				<ATTRIBUTE NAME="in" VALUE="str3" />
				<ATTRIBUTE NAME="d1.id" VALUE="str3" />
				<ATTRIBUTE NAME="d1.type" VALUE="street" />
				<ATTRIBUTE NAME="d1.name" VALUE="rua garret" />
			</ATTRIBUTE-SET2>
		</CONTEXT>
		<CONTEXT ID ="18" SEQ="1698" STATUS="ok" AGREEMENT="yes" ANNOTATOR="1"  SIZE1="6"  SIZE2="6" WORD-STRING ="as farmacias da rua do ouro">
			<ATTRIBUTE-SET1 TARGET.ID="drug2">
				<ATTRIBUTE NAME="type" VALUE="drugstore" />
				<ATTRIBUTE NAME="in" VALUE="str11" />
				<ATTRIBUTE NAME="d1.id" VALUE="str11" />
				<ATTRIBUTE NAME="d1.type" VALUE="street" />
				<ATTRIBUTE NAME="d1.name" VALUE="rua do ouro" />
			</ATTRIBUTE-SET1>
			<ATTRIBUTE-SET2 TARGET.ID="drug3">
				<ATTRIBUTE NAME="type" VALUE="drugstore" />
				<ATTRIBUTE NAME="in" VALUE="str11" />
				<ATTRIBUTE NAME="d1.id" VALUE="str11" />
				<ATTRIBUTE NAME="d1.type" VALUE="street" />
				<ATTRIBUTE NAME="d1.name" VALUE="rua do ouro" />
			</ATTRIBUTE-SET2>
		</CONTEXT>
		<CONTEXT ID ="19" SEQ="1697" STATUS="ok" AGREEMENT="no" ANNOTATOR="1"  SIZE1="8"  SIZE2="0" WORD-STRING ="a farmacia cortez na travessa da rua do ouro">
			<ATTRIBUTE-SET1 TARGET.ID="drug4">
				<ATTRIBUTE NAME="type" VALUE="drugstore" />
				<ATTRIBUTE NAME="name" VALUE="cortez" />
				<ATTRIBUTE NAME="in" VALUE="str11" />
				<ATTRIBUTE NAME="d1.id" VALUE="str11" />
				<ATTRIBUTE NAME="d1.type" VALUE="street" />
				<ATTRIBUTE NAME="d1.name" VALUE="rua do ouro" />
				<ATTRIBUTE NAME="d1.other" VALUE="corner" />
			</ATTRIBUTE-SET1>
		</CONTEXT>
		<CONTEXT ID ="20" SEQ="1700" STATUS="ok" AGREEMENT="no" ANNOTATOR="2"  SIZE1="6"  SIZE2="2" WORD-STRING ="os restaurantes o sacramento na calcada do sacramento, ou a taberna do dragao">
			<ATTRIBUTE-SET1 TARGET.ID="rest4">
				<ATTRIBUTE NAME="type" VALUE="restaurant" />
				<ATTRIBUTE NAME="name" VALUE="o sacramento" />
				<ATTRIBUTE NAME="in" VALUE="str16" />
				<ATTRIBUTE NAME="d1.id" VALUE="str16" />
				<ATTRIBUTE NAME="d1.name" VALUE="calcada do sacramento" />
			</ATTRIBUTE-SET1>
			<ATTRIBUTE-SET2 TARGET.ID="rest5">
				<ATTRIBUTE NAME="name" VALUE="taberna do chiado" />
			</ATTRIBUTE-SET2>
		</CONTEXT>
</TRIAL>
