<?xml version="1.0"?>
<!DOCTYPE TRIAL SYSTEM "furniture.dtd">
<TRIAL CARDINALITY="1" CONDITION="-LOC" DOMAIN="furniture" ID="s78t4"
	SIMILARITY="similar">
	<DOMAIN>
		<ENTITY ID="121" IMAGE="fanLeftBlueSmall.gif" TYPE="target">
			<ATTRIBUTE NAME="colour" TYPE="literal" VALUE="blue" />
			<ATTRIBUTE NAME="orientation" TYPE="literal" VALUE="left" />
			<ATTRIBUTE NAME="type" TYPE="literal" VALUE="fan" />
			<ATTRIBUTE NAME="size" TYPE="literal" VALUE="small" />
			<ATTRIBUTE NAME="x-dimension" TYPE="gradable" VALUE="3" />
			<ATTRIBUTE NAME="y-dimension" TYPE="gradable" VALUE="2" />
		</ENTITY>
		<ENTITY ID="122" IMAGE="fanLeftGreenSmall.gif"
			TYPE="distractor">
			<ATTRIBUTE NAME="colour" TYPE="literal" VALUE="green" />
			<ATTRIBUTE NAME="orientation" TYPE="literal" VALUE="left" />
			<ATTRIBUTE NAME="type" TYPE="literal" VALUE="fan" />
			<ATTRIBUTE NAME="size" TYPE="literal" VALUE="small" />
			<ATTRIBUTE NAME="x-dimension" TYPE="gradable" VALUE="5" />
			<ATTRIBUTE NAME="y-dimension" TYPE="gradable" VALUE="2" />
		</ENTITY>
		<ENTITY ID="57" IMAGE="fanLeftBlueLarge.gif"
			TYPE="distractor">
			<ATTRIBUTE NAME="colour" TYPE="literal" VALUE="blue" />
			<ATTRIBUTE NAME="orientation" TYPE="literal" VALUE="left" />
			<ATTRIBUTE NAME="type" TYPE="literal" VALUE="fan" />
			<ATTRIBUTE NAME="size" TYPE="literal" VALUE="large" />
			<ATTRIBUTE NAME="x-dimension" TYPE="gradable" VALUE="2" />
			<ATTRIBUTE NAME="y-dimension" TYPE="gradable" VALUE="2" />
		</ENTITY>
		<ENTITY ID="52" IMAGE="fanBackRedLarge.gif" TYPE="distractor">
			<ATTRIBUTE NAME="colour" TYPE="literal" VALUE="red" />
			<ATTRIBUTE NAME="orientation" TYPE="literal" VALUE="back" />
			<ATTRIBUTE NAME="type" TYPE="literal" VALUE="fan" />
			<ATTRIBUTE NAME="size" TYPE="literal" VALUE="large" />
			<ATTRIBUTE NAME="x-dimension" TYPE="gradable" VALUE="3" />
			<ATTRIBUTE NAME="y-dimension" TYPE="gradable" VALUE="1" />
		</ENTITY>
		<ENTITY ID="106" IMAGE="sofaLeftGreenSmall.gif"
			TYPE="distractor">
			<ATTRIBUTE NAME="colour" TYPE="literal" VALUE="green" />
			<ATTRIBUTE NAME="orientation" TYPE="literal" VALUE="left" />
			<ATTRIBUTE NAME="type" TYPE="literal" VALUE="sofa" />
			<ATTRIBUTE NAME="size" TYPE="literal" VALUE="small" />
			<ATTRIBUTE NAME="x-dimension" TYPE="gradable" VALUE="4" />
			<ATTRIBUTE NAME="y-dimension" TYPE="gradable" VALUE="1" />
		</ENTITY>
		<ENTITY ID="41" IMAGE="sofaLeftBlueLarge.gif"
			TYPE="distractor">
			<ATTRIBUTE NAME="colour" TYPE="literal" VALUE="blue" />
			<ATTRIBUTE NAME="orientation" TYPE="literal" VALUE="left" />
			<ATTRIBUTE NAME="type" TYPE="literal" VALUE="sofa" />
			<ATTRIBUTE NAME="size" TYPE="literal" VALUE="large" />
			<ATTRIBUTE NAME="x-dimension" TYPE="gradable" VALUE="5" />
			<ATTRIBUTE NAME="y-dimension" TYPE="gradable" VALUE="1" />
		</ENTITY>
		<ENTITY ID="36" IMAGE="sofaBackRedLarge.gif"
			TYPE="distractor">
			<ATTRIBUTE NAME="colour" TYPE="literal" VALUE="red" />
			<ATTRIBUTE NAME="orientation" TYPE="literal" VALUE="back" />
			<ATTRIBUTE NAME="type" TYPE="literal" VALUE="sofa" />
			<ATTRIBUTE NAME="size" TYPE="literal" VALUE="large" />
			<ATTRIBUTE NAME="x-dimension" TYPE="gradable" VALUE="4" />
			<ATTRIBUTE NAME="y-dimension" TYPE="gradable" VALUE="3" />
		</ENTITY>
	</DOMAIN>
	<STRING-DESCRIPTION>
		It is a blue fan in the middle of the page and is small. It is
		facing to the left.
	</STRING-DESCRIPTION>
	<DESCRIPTION NUM="singular">
		It is
		<DET ID="8001" VALUE="indefinite">a</DET>
		<ATTRIBUTE ID="a1" NAME="colour" VALUE="blue">blue</ATTRIBUTE>
		<ATTRIBUTE ID="a2" NAME="type" VALUE="fan">fan</ATTRIBUTE>
		<META-ATTRIBUTE ID="a269" NAME="location" VALUE="middle">
			<ATTRIBUTE ID="a3" NAME="y-dimension" VALUE="2" />
			<ATTRIBUTE ID="a4" NAME="x-dimension" VALUE="3" />
			in the middle of the page
		</META-ATTRIBUTE>
		and
		<ATTRIBUTE ID="a5" NAME="size" VALUE="small">
			is small
		</ATTRIBUTE>
		.
		<ATTRIBUTE ID="a6" NAME="orientation" VALUE="left">
			It is facing to the left
		</ATTRIBUTE>
		.
	</DESCRIPTION>
	<ATTRIBUTE-SET>
		<ATTRIBUTE ID="a6" NAME="orientation" VALUE="left"></ATTRIBUTE>
		<ATTRIBUTE ID="a5" NAME="size" VALUE="small"></ATTRIBUTE>
		<ATTRIBUTE ID="a4" NAME="x-dimension" VALUE="3" />
		<ATTRIBUTE ID="a3" NAME="y-dimension" VALUE="2" />
		<ATTRIBUTE ID="a2" NAME="type" VALUE="fan"></ATTRIBUTE>
		<ATTRIBUTE ID="a1" NAME="colour" VALUE="blue"></ATTRIBUTE>
	</ATTRIBUTE-SET>
</TRIAL>
